<Shop>
	<Item>
		<speed>+2</speed>
		<rotate>+3</rotate>
		<model>UI/ShipsUI/Ship_1</model>
		<price>2000</price>
    <id>0</id>
    <ship>Ship/Ship_1</ship>
	</Item>
	<Item>
		<speed>+4</speed>
		<rotate>+6</rotate>
		<model>UI/ShipsUI/Ship_2</model>
		<price>3000</price>
    <id>1</id>
    <ship>Ship/Ship_2</ship>
	</Item>
	<Item>
		<speed>+8</speed>
		<rotate>+10</rotate>
		<model>UI/ShipsUI/Ship_3</model>
		<price>5000</price>
    <id>2</id>
    <ship>Ship/Ship_3</ship>
	</Item>
	<Item>
		<speed>+15</speed>
		<rotate>+20</rotate>
		<model>UI/ShipsUI/Ship_4</model>
		<price>8000</price>
    <id>3</id>
    <ship>Ship/Ship_4</ship>
	</Item>	
</Shop>